lib_ml/__init__.py
lib_ml/preprocessing.py
lib_ml/version.py
lib_ml_remla_team14_a2-5.0.0.dist-info/METADATA
lib_ml_remla_team14_a2-5.0.0.dist-info/WHEEL
lib_ml_remla_team14_a2-5.0.0.dist-info/top_level.txt
lib_ml_remla_team14_a2-5.0.0.dist-info/RECORD
