Metadata-Version: 2.1
Name: lib-ml-remla-team14-a2
Version: 5.0.0
Summary: A ML preprocessing library.
Home-page: https://github.com/07Liyang/lib_ml
Author: Yang Li
Author-email: ly20000325@gmail.com
License: UNKNOWN
Platform: UNKNOWN
Classifier: Development Status :: 3 - Alpha
Classifier: Intended Audience :: Developers
Classifier: Topic :: Software Development :: Build Tools
Classifier: License :: OSI Approved :: MIT License
Classifier: Programming Language :: Python :: 3
Classifier: Programming Language :: Python :: 3.7
Classifier: Programming Language :: Python :: 3.8
Classifier: Programming Language :: Python :: 3.9
Requires-Python: >=3.7
Requires-Dist: numpy
Requires-Dist: tensorflow
